git2s3/__init__.py
git2s3/config.py
git2s3/exc.py
git2s3/main.py
git2s3/s3.py
git2s3/squire.py
git2s3-0.1.1.dist-info/licenses/LICENSE
git2s3-0.1.1.dist-info/METADATA
git2s3-0.1.1.dist-info/WHEEL
git2s3-0.1.1.dist-info/entry_points.txt
git2s3-0.1.1.dist-info/top_level.txt
git2s3-0.1.1.dist-info/RECORD
