Metadata-Version: 2.4
Name: git2s3
Version: 0.1.1
Summary: Backup GitHub projects to AWS S3
Author-email: Vignesh Rao <svignesh1793@gmail.com>
License: MIT License
Project-URL: Homepage, https://github.com/thevickypedia/git2s3
Project-URL: Docs, https://thevickypedia.github.io/git2s3
Project-URL: Source, https://github.com/thevickypedia/git2s3
Project-URL: Bug Tracker, https://github.com/thevickypedia/git2s3/issues
Project-URL: Release Notes, https://github.com/thevickypedia/git2s3/blob/main/release_notes.rst
Keywords: git2s3,backup
Classifier: License :: OSI Approved :: MIT License
Classifier: Programming Language :: Python :: 3
Classifier: Development Status :: 5 - Production/Stable
Classifier: Operating System :: MacOS :: MacOS X
Classifier: Operating System :: Microsoft :: Windows
Classifier: Operating System :: POSIX :: Linux
Classifier: Topic :: System :: Archiving :: Backup
Requires-Python: >=3.10
License-File: LICENSE
Requires-Dist: boto3~=1.40.19
Requires-Dist: botocore~=1.40.19
Requires-Dist: click~=8.2.1
Requires-Dist: pydantic~=2.11.7
Requires-Dist: pydantic-settings~=2.10.1
Requires-Dist: PyYAML~=6.0.2
Requires-Dist: requests~=2.32.5
Provides-Extra: dev
Requires-Dist: sphinx==5.1.1; extra == "dev"
Requires-Dist: pre-commit; extra == "dev"
Requires-Dist: recommonmark; extra == "dev"
Requires-Dist: gitverse; extra == "dev"
Dynamic: license-file
